feat/__init__.py
feat/feat.py
feat/pyfeat.cpython-38-x86_64-linux-gnu.so
feat/versionstr.py
feat_ml-0.5.2.dist-info/LICENSE
feat_ml-0.5.2.dist-info/METADATA
feat_ml-0.5.2.dist-info/WHEEL
feat_ml-0.5.2.dist-info/top_level.txt
feat_ml-0.5.2.dist-info/RECORD
